LICENSE
MANIFEST.in
README.md
setup.py
pytest_html/__init__.py
pytest_html/extras.py
pytest_html/hooks.py
pytest_html/html_report.py
pytest_html/outcome.py
pytest_html/plugin.py
pytest_html/result.py
pytest_html/util.py
pytest_html/resources/main.js
pytest_html/resources/style.css
pytest_html_cn.egg-info/PKG-INFO
pytest_html_cn.egg-info/SOURCES.txt
pytest_html_cn.egg-info/dependency_links.txt
pytest_html_cn.egg-info/entry_points.txt
pytest_html_cn.egg-info/requires.txt
pytest_html_cn.egg-info/top_level.txt
tests/test_pytest_html_cn.py