Metadata-Version: 2.1
Name: pytest-html-cn
Version: 3.1.3
Summary: pytest plugin for generating HTML reports
Home-page: https://github.com/hanzhichao/pytest-html-cn
Author: Han Zhichao
Author-email: superhin@126.com
License: Mozilla Public License 2.0 (MPL 2.0)
Keywords: py.test pytest html report
Classifier: Development Status :: 5 - Production/Stable
Classifier: Framework :: Pytest
Classifier: Intended Audience :: Developers
Classifier: License :: OSI Approved :: Mozilla Public License 2.0 (MPL 2.0)
Classifier: Operating System :: POSIX
Classifier: Operating System :: Microsoft :: Windows
Classifier: Operating System :: MacOS :: MacOS X
Classifier: Topic :: Software Development :: Quality Assurance
Classifier: Topic :: Software Development :: Testing
Classifier: Topic :: Utilities
Classifier: Programming Language :: Python
Classifier: Programming Language :: Python :: 3
Classifier: Programming Language :: Python :: 3.6
Classifier: Programming Language :: Python :: 3.7
Classifier: Programming Language :: Python :: 3.8
Classifier: Programming Language :: Python :: 3.9
Classifier: Programming Language :: Python :: 3 :: Only
Requires-Python: >=3.6
License-File: LICENSE
Requires-Dist: pytest!=6.0.0,>=5.0
Requires-Dist: pytest-metadata
Requires-Dist: py
